celery_redis_plus/__init__.py
celery_redis_plus/bootstep.py
celery_redis_plus/constants.py
celery_redis_plus/py.typed
celery_redis_plus/signals.py
celery_redis_plus/transport.py
celery_redis_plus/transport_enqueue_due_messages.lua
celery_redis_plus/transport_requeue_message.lua
celery_redis_plus-0.2.3.dist-info/METADATA
celery_redis_plus-0.2.3.dist-info/WHEEL
celery_redis_plus-0.2.3.dist-info/entry_points.txt
celery_redis_plus-0.2.3.dist-info/licenses/LICENSE
celery_redis_plus-0.2.3.dist-info/RECORD
