Metadata-Version: 2.4
Name: celery-redis-plus
Version: 0.2.3
Summary: Enhanced Kombu Redis transport for Celery
Project-URL: Homepage, https://github.com/oliverhaas/celery-redis-plus
Project-URL: Documentation, https://oliverhaas.github.io/celery-redis-plus/
Project-URL: Repository, https://github.com/oliverhaas/celery-redis-plus.git
Author-email: Oliver Haas <ohaas@e1plus.de>
License: MIT
License-File: LICENSE
Keywords: celery,kombu,message-queue,priority-queue,redis
Classifier: Development Status :: 3 - Alpha
Classifier: License :: OSI Approved :: MIT License
Classifier: Operating System :: OS Independent
Classifier: Programming Language :: Python :: 3
Classifier: Programming Language :: Python :: 3.13
Classifier: Programming Language :: Python :: 3.14
Classifier: Topic :: System :: Distributed Computing
Classifier: Typing :: Typed
Requires-Python: >=3.13
Requires-Dist: celery>=5.5.0
Requires-Dist: kombu>=5.5.0
Provides-Extra: hiredis
Requires-Dist: redis[hiredis]<8,>=7.1.0; extra == 'hiredis'
Provides-Extra: libvalkey
Requires-Dist: valkey[libvalkey]<7,>=6.1.0; extra == 'libvalkey'
Provides-Extra: redis
Requires-Dist: redis<8,>=7.1.0; extra == 'redis'
Provides-Extra: valkey
Requires-Dist: valkey<7,>=6.1.0; extra == 'valkey'
